airmise/__init__.py
airmise/__main__.py
airmise/client.py
airmise/codec.py
airmise/codec2.py
airmise/const.py
airmise/environment.py
airmise/export.py
airmise/master.py
airmise/remote_control.py
airmise/server.py
airmise/slave.py
airmise/socket_wrapper.py
airmise/util.py
airmise/webapp.py
airmise-2.0.0.dist-info/METADATA
airmise-2.0.0.dist-info/WHEEL
airmise-2.0.0.dist-info/RECORD
