Metadata-Version: 2.3
Name: airmise
Version: 2.0.0
Summary: The native experience of calling remote functions, like local ones.
Author: Likianta
Author-email: likianta@foxmail.com
Requires-Python: >=3.8
Classifier: Programming Language :: Python :: 3
Classifier: Programming Language :: Python :: 3.8
Classifier: Programming Language :: Python :: 3.9
Classifier: Programming Language :: Python :: 3.10
Classifier: Programming Language :: Python :: 3.11
Classifier: Programming Language :: Python :: 3.12
Classifier: Programming Language :: Python :: 3.13
Requires-Dist: argsense (>=1.1.0,<2.0.0)
Requires-Dist: lk-logger (>=6.0.6,<7.0.0)
Requires-Dist: lk-utils (>=3.4.0,<4.0.0)
Project-URL: Homepage, https://github.com/likianta/airmise
